monk_pytorch_finetune_test/__init__.py
monk_pytorch_finetune_test/coco_eval.py
monk_pytorch_finetune_test/coco_utils.py
monk_pytorch_finetune_test/data_loader_class.py
monk_pytorch_finetune_test/detector_prototype.py
monk_pytorch_finetune_test/engine.py
monk_pytorch_finetune_test/inference_prototype.py
monk_pytorch_finetune_test/transforms.py
monk_pytorch_finetune_test/utils.py
monk_obj_test2-0.0.12.dist-info/LICENSE.md
monk_obj_test2-0.0.12.dist-info/METADATA
monk_obj_test2-0.0.12.dist-info/WHEEL
monk_obj_test2-0.0.12.dist-info/top_level.txt
monk_obj_test2-0.0.12.dist-info/RECORD
