Metadata-Version: 2.1
Name: monk-obj-test2
Version: 0.0.12
Summary: Monk Object Detection's 2_pytorch_finetune
Home-page: https://github.com/Tessellate-Imaging/Monk_Object_Detection
Author: Tessellate Imaging
Author-email: abhishek@tessellateimaging.com
License: UNKNOWN
Platform: UNKNOWN
Classifier: Programming Language :: Python :: 3
Classifier: License :: OSI Approved :: Apache Software License
Classifier: Operating System :: OS Independent
Classifier: Environment :: GPU :: NVIDIA CUDA :: 9.0
Requires-Python: >=3.6
Requires-Dist: numpy
Requires-Dist: scipy
Requires-Dist: tqdm
Requires-Dist: pillow
Requires-Dist: opencv-python
Requires-Dist: cython
Requires-Dist: jupyter
Requires-Dist: notebook
Requires-Dist: pandas
Requires-Dist: matplotlib
Requires-Dist: xmltodict
Requires-Dist: torchvision (==0.5.0)
Requires-Dist: torch (==1.4.0)
Requires-Dist: pycocotools
